pyrizz/__init__.py
pyrizz/__main__.py
pyrizz/pickuplines.py
pyrizz/pyrizz.py
pyrizz/templates.py
pyrizz/data/ascii_art.txt
pyrizz-1.1.2.dist-info/LICENSE
pyrizz-1.1.2.dist-info/METADATA
pyrizz-1.1.2.dist-info/WHEEL
pyrizz-1.1.2.dist-info/entry_points.txt
pyrizz-1.1.2.dist-info/top_level.txt
pyrizz-1.1.2.dist-info/RECORD
