Metadata-Version: 2.1
Name: pyrizz
Version: 1.1.2
Summary: A package where users can receive pick up lines, rate pickup lines and add pickup lines
Author-email: Aditya Pandhare <adityapandhare44@gmail.com>, Anzhelika Nastashchuk <anzhelika.nastashchuk@gmail.com>, Baani Pasrsija <baanipasrija25@gmail.com>, Zander Chen <ccczy2002@gmail.com>
License: GNU GENERAL PUBLIC LICENSE
Project-URL: Homepage, https://github.com/software-students-fall2023/3-python-package-exercise-experientia
Project-URL: Repository, https://github.com/software-students-fall2023/3-python-package-exercise-experientia.git
Project-URL: Bug Tracker, https://github.com/software-students-fall2023/3-python-package-exercise-experientia/issues
Keywords: python,package,build,pyrizz,pickup-line
Classifier: Programming Language :: Python :: 3
Classifier: Intended Audience :: Education
Classifier: License :: OSI Approved :: GNU General Public License v3 (GPLv3)
Classifier: Operating System :: OS Independent
Requires-Python: >=3.7
License-File: LICENSE
Provides-Extra: dev
Requires-Dist: pytest ; extra == 'dev'
